defaultable/__init__.py
defaultable/defaultable.py
defaultable-0.1.1.dist-info/LICENSE
defaultable-0.1.1.dist-info/METADATA
defaultable-0.1.1.dist-info/WHEEL
defaultable-0.1.1.dist-info/top_level.txt
defaultable-0.1.1.dist-info/RECORD
