Metadata-Version: 2.1
Name: defaultable
Version: 0.1.1
Summary: A simple Python package for defaultable abstract base classes
Home-page: UNKNOWN
Author: Tal Fiderer
Author-email: talfiderer@gmail.com
License: UNKNOWN
Platform: UNKNOWN
Classifier: Programming Language :: Python :: 3
Classifier: License :: OSI Approved :: MIT License
Classifier: Operating System :: OS Independent
Requires-Python: >=3.6
License-File: LICENSE
